{
  "articles": [
    {
      "id": 3,
      "title": "疲労回復3日間リセットプログラム",
      "genre": "健康",
      "date": "2026-04-10",
      "summary": "金曜夜から月曜昼まで、慢性疲労を根本からリセットする72時間のルーティン。睡眠・食事・入浴・軽運動を科学的に組み合わせたプログラム。",
      "tags": [
        "疲労回復",
        "睡眠",
        "ルーティン"
      ],
      "readTime": 5,
      "file": "articles/fatigue_reset_3days.html"
    },
    {
      "id": 14,
      "title": "2026スキンケア",
      "genre": "健康",
      "date": "2026-05-04",
      "summary": "情報過多のスキンケアを整理し、今年優先したい11の習慣と選び方を科学的根拠をもとに解説。保湿・日焼け止め・食事・睡眠を軸にした実践ガイド。",
      "tags": [
        "スキンケア",
        "保湿",
        "日焼け止め"
      ],
      "readTime": 7,
      "file": "articles/skincare_video_transcription_7.html"
    },
    {
      "id": 15,
      "title": "睡眠の質を立て直す2週間ガイド",
      "genre": "ライフスタイル",
      "date": "2026-05-04",
      "summary": "夜更かしの背景把握から環境調整・就寝ルーティン・日中の設計まで、自己コントロール・環境・習慣の3軸で睡眠を整え直す実践メモ。",
      "tags": [
        "睡眠",
        "習慣",
        "ルーティン"
      ],
      "readTime": 5,
      "file": "articles/sleep_quality_reset_guide.html"
    },
    {
      "id": 17,
      "title": "30代からの老化を遅らせる13の実践",
      "genre": "健康",
      "date": "2026-05-04",
      "summary": "食事・運動・調理法・ストレス管理を一つの生活設計として統合した、30代からのアンチエイジング実践ガイド。",
      "tags": [
        "老化防止",
        "食事",
        "運動"
      ],
      "readTime": 5,
      "file": "articles/anti_aging_13_rules_30s.html"
    },
    {
      "id": 19,
      "title": "信頼をつくる聞く力の鍛え方",
      "genre": "ライフスタイル",
      "date": "2026-05-04",
      "summary": "相手の本心を無理に読むより、理解しようとする聞き方を磨くほうが信頼関係は育つ。アクティブリスニングの3つの基礎と7つのテクニックを実践形式で解説。",
      "tags": [
        "コミュニケーション",
        "傾聴",
        "信頼"
      ],
      "readTime": 5,
      "file": "articles/active_listening_trust_building.html"
    },
    {
      "id": 20,
      "title": "時間不足感を整える実践ガイド",
      "genre": "ライフスタイル",
      "date": "2026-05-04",
      "summary": "忙しさそのものより、時間の捉え方を整えるほうが余白を取り戻しやすい。時間認知の歪みと「時間飢餓」「時間汚染」の2パターンを解消する具体策を解説。",
      "tags": [
        "時間管理",
        "ストレス",
        "習慣"
      ],
      "readTime": 4,
      "file": "articles/time_scarcity_reset.html"
    },
    {
      "id": 21,
      "title": "コンフォートゾーンを抜けて成長を作る",
      "genre": "ライフスタイル",
      "date": "2026-05-04",
      "summary": "怖さを避けるのではなく、怖さの先にある学習と成長を見据えて行動を選ぶための整理。4つのゾーンの仕組みと、挑戦を設計・継続するための実践ガイド。",
      "tags": [
        "成長",
        "挑戦",
        "行動設計"
      ],
      "readTime": 5,
      "file": "articles/comfort_zone_growth.html"
    },
    {
      "id": 22,
      "title": "視点を増やすためのクリティカルシンキング",
      "genre": "ライフスタイル",
      "date": "2026-05-04",
      "summary": "思い込みを崩し、選択肢を増やし、自分の判断精度を上げるための実践的な考え方を整理する。",
      "tags": [],
      "readTime": 2,
      "file": "articles/critical_thinking.html"
    },
    {
      "id": 23,
      "title": "HIITを短時間で最大化する実践ガイド",
      "genre": "健康",
      "date": "2026-05-04",
      "summary": "時間がない人でも、心肺機能と代謝を効率よく底上げしやすい運動設計を整理。",
      "tags": [
        "HIIT",
        "トレーニング",
        "有酸素"
      ],
      "readTime": 2,
      "file": "articles/hiit_total_benefits.html"
    },
    {
      "id": 24,
      "title": "散歩を脳と気分の土台にする方法",
      "genre": "ライフスタイル",
      "date": "2026-05-04",
      "summary": "強い運動より先に、続けやすい歩行習慣で認知機能とメンタルを整える。",
      "tags": [
        "散歩",
        "脳科学",
        "習慣"
      ],
      "readTime": 2,
      "file": "articles/walking_daily_benefits.html"
    },
    {
      "id": 25,
      "title": "30代からの老化を遅らせる13の基本",
      "genre": "健康",
      "date": "2026-05-04",
      "summary": "急な老け込みを防ぐには、食事・運動・炎症管理を生活の中で同時に整える。",
      "tags": [
        "老化防止",
        "食事",
        "運動"
      ],
      "readTime": 3,
      "file": "articles/anti_aging_13_rules_practical.html"
    },
    {
      "id": 26,
      "title": "ドーパミンに振り回されない生活設計",
      "genre": "ライフスタイル",
      "date": "2026-05-04",
      "summary": "集中力が落ちる背景には、意志の弱さよりもスマホ、食事、睡眠、報酬設計の崩れがある。ドーパミンを敵視するのではなく、刺激の質を整え、静かな集中力へ戻す実践を整理する。",
      "tags": [
        "ドーパミン",
        "集中力",
        "デトックス"
      ],
      "readTime": 5,
      "file": "articles/dopamine_detox_reset_guide.html"
    }
  ]
}
